crnsimulator/__init__.py
crnsimulator/crn_parser.py
crnsimulator/odelib_template.py
crnsimulator/plotting.py
crnsimulator/reactiongraph.py
crnsimulator/simulator.py
crnsimulator/solver.py
tests/__init__.py
tests/test_crn_parser.py
tests/test_reactiongraph.py
tests/test_solver.py
crnsimulator-0.9.dist-info/LICENSE
crnsimulator-0.9.dist-info/METADATA
crnsimulator-0.9.dist-info/WHEEL
crnsimulator-0.9.dist-info/entry_points.txt
crnsimulator-0.9.dist-info/top_level.txt
crnsimulator-0.9.dist-info/RECORD
