Metadata-Version: 2.1
Name: crnsimulator
Version: 0.9
Summary: Simulate CRNs using ODEs.
Home-page: https://github.com/bad-ants-fleet/crnsimulator
Author: Stefan Badelt
Author-email: bad-ants-fleet@posteo.eu
Maintainer: Stefan Badelt
Maintainer-email: bad-ants-fleet@posteo.eu
License: MIT
Platform: UNKNOWN
Classifier: Development Status :: 4 - Beta
Classifier: Programming Language :: Python :: 3.7
Classifier: Programming Language :: Python :: 3.8
Classifier: Programming Language :: Python :: 3.9
Classifier: Intended Audience :: Science/Research
Requires-Python: >=3.7
Requires-Dist: scipy (>=0.16.1)
Requires-Dist: sympy (>=0.7.6.1)
Requires-Dist: pyparsing
Requires-Dist: numpy
Requires-Dist: matplotlib
Requires-Dist: seaborn
